openapi2tools/__init__.py
openapi2tools/tool.py
openapi2tools-0.3.dist-info/LICENSE
openapi2tools-0.3.dist-info/METADATA
openapi2tools-0.3.dist-info/WHEEL
openapi2tools-0.3.dist-info/entry_points.txt
openapi2tools-0.3.dist-info/top_level.txt
openapi2tools-0.3.dist-info/RECORD
