Metadata-Version: 2.1
Name: openapi2tools
Version: 0.3
Summary: A library to convert an OpenAPI spec to LangGraph tools
Home-page: https://github.com/taowenwei/openapi2tools
Author: Wenwei Tao
Author-email: taowenwei@hotmail.com
Classifier: Programming Language :: Python :: 3
Classifier: License :: OSI Approved :: MIT License
Classifier: Operating System :: OS Independent
Requires-Python: >=3.6
License-File: LICENSE
